LICENSE.txt
README.md
setup.py
codigofacilitofran/__init__.py
codigofacilitofran/__main__.py
codigofacilitofran/workshops.py
codigofacilitofran.egg-info/PKG-INFO
codigofacilitofran.egg-info/SOURCES.txt
codigofacilitofran.egg-info/dependency_links.txt
codigofacilitofran.egg-info/entry_points.txt
codigofacilitofran.egg-info/requires.txt
codigofacilitofran.egg-info/top_level.txt