Metadata-Version: 2.1
Name: codigofacilitofran
Version: 0.0.3
Summary: Este paquete permite consumir API
Home-page: https://github.com/fguedezo/codigofacilito_package
Author: Francisco Guedez
Author-email: fguedez1311@gmail.com
License: MIT
Keywords: codigofacilito
Platform: UNKNOWN
Classifier: Development Status :: 3 - Alpha
Classifier: Intended Audience :: Developers
Classifier: Topic :: Software Development :: Build Tools
Classifier: License :: OSI Approved :: MIT License
Classifier: Programming Language :: Python :: 3
License-File: LICENSE.txt
